{"user_id":1,"event_log":[{"time":"1016","selection":"1","menu_number":"2","num_wrong":"0","type":"practice","onset":"500","adaptive_accuracy":"75"},{"time":"1248","selection":"1","menu_number":"1","num_wrong":"0","type":"onset 500","onset":"500","adaptive_accuracy":"75"},{"time":"931","selection":"0","menu_number":"3","num_wrong":"0","type":"onset 0","onset":"0","adaptive_accuracy":"75"},{"time":"1163","selection":"2","menu_number":"3","num_wrong":"0","type":"onset 250","onset":"250","adaptive_accuracy":"75"}]}